coingecko/__init__.py
coingecko/coingecko.py
coingecko/utils.py
py_coingecko_client-1.0.0.dist-info/LICENSE
py_coingecko_client-1.0.0.dist-info/METADATA
py_coingecko_client-1.0.0.dist-info/WHEEL
py_coingecko_client-1.0.0.dist-info/top_level.txt
py_coingecko_client-1.0.0.dist-info/RECORD
