Metadata-Version: 2.1
Name: py-coingecko-client
Version: 1.0.0
Summary: Coingecko API wrapper
Home-page: https://github.com/crypto-kitchenette/py-coingecko
Author: Crypto Kitchenette Team
License: MIT
Platform: UNKNOWN
Classifier: License :: OSI Approved :: MIT License
Classifier: Programming Language :: Python :: 3
Classifier: Programming Language :: Python :: 3.7
License-File: LICENSE
Requires-Dist: requests
